pixelcms_shop_server-0.0.1.dist-info/DESCRIPTION.rst
pixelcms_shop_server-0.0.1.dist-info/METADATA
pixelcms_shop_server-0.0.1.dist-info/RECORD
pixelcms_shop_server-0.0.1.dist-info/SOURCES.txt.py
pixelcms_shop_server-0.0.1.dist-info/WHEEL
pixelcms_shop_server-0.0.1.dist-info/dependency_links.txt.py
pixelcms_shop_server-0.0.1.dist-info/metadata.json
pixelcms_shop_server-0.0.1.dist-info/requires.txt.py
pixelcms_shop_server-0.0.1.dist-info/top_level.txt
pixelcms_shop_server-0.0.1.dist-info/top_level.txt.py
shop/__init__.py
shop/apps.py
shop/settings.py
shop/urls_api.py
shop/urls_routes.py
shop/__pycache__/__init__.cpython-35.pyc
shop/__pycache__/apps.cpython-35.pyc
shop/__pycache__/settings.cpython-35.pyc
shop/__pycache__/urls_api.cpython-35.pyc
shop/__pycache__/urls_routes.cpython-35.pyc
shop/catalog/__init__.py
shop/catalog/admin.py
shop/catalog/apps.py
shop/catalog/models.py
shop/catalog/serializers.py
shop/catalog/urls_api.py
shop/catalog/urls_routes.py
shop/catalog/views_api.py
shop/catalog/views_routes.py
shop/catalog/__pycache__/__init__.cpython-35.pyc
shop/catalog/__pycache__/admin.cpython-35.pyc
shop/catalog/__pycache__/apps.cpython-35.pyc
shop/catalog/__pycache__/models.cpython-35.pyc
shop/catalog/__pycache__/serializers.cpython-35.pyc
shop/catalog/__pycache__/urls_api.cpython-35.pyc
shop/catalog/__pycache__/urls_routes.cpython-35.pyc
shop/catalog/__pycache__/views.cpython-35.pyc
shop/catalog/__pycache__/views_api.cpython-35.pyc
shop/catalog/__pycache__/views_routes.cpython-35.pyc
shop/catalog/static/admin/shop/catalog/productAttribute.js
shop/config/__init__.py
shop/config/admin.py
shop/config/apps.py
shop/config/models.py
shop/config/__pycache__/__init__.cpython-35.pyc
shop/config/__pycache__/admin.cpython-35.pyc
shop/config/__pycache__/apps.cpython-35.pyc
shop/config/__pycache__/models.cpython-35.pyc
shop/locale/pl/LC_MESSAGES/django.mo
shop/locale/pl/LC_MESSAGES/django.po
shop/migrations/0001_initial.py
shop/migrations/0002_auto_20161230_1608.py
shop/migrations/0003_remove_order_cart.py
shop/migrations/0004_order_customer.py
shop/migrations/0005_auto_20161230_1833.py
shop/migrations/0006_auto_20161230_1907.py
shop/migrations/0007_auto_20161230_2117.py
shop/migrations/0008_auto_20161230_2126.py
shop/migrations/0009_auto_20161230_2131.py
shop/migrations/0010_auto_20161230_2134.py
shop/migrations/0011_auto_20161230_2135.py
shop/migrations/0012_auto_20161230_2136.py
